{
  "phase": "Phase 9: Feature Set Optimization",
  "date": "2025-10-06",
  "best_feature_set": "all_features",
  "n_features": 88,
  "hyperparameters": {
    "colsample_bylevel": 0.5209373494866074,
    "colsample_bynode": 0.7520225915617307,
    "colsample_bytree": 0.5298311116653025,
    "gamma": 3.9248980123423016,
    "learning_rate": 0.26913665694390104,
    "max_delta_step": 2,
    "max_depth": 5,
    "max_leaves": 22,
    "min_child_weight": 5,
    "n_estimators": 427,
    "reg_alpha": 9.924232665070894,
    "reg_lambda": 7.562339421860171,
    "scale_pos_weight": 1.629032868306186,
    "subsample": 0.8563561641032563
  },
  "performance": {
    "cv_roc_auc": 0.7265991471215352,
    "cv_roc_auc_std": 0.04817096974234974,
    "cv_pr_auc": 0.28934458855724665,
    "train_roc_auc": 0.8321479374110953,
    "val_roc_auc": 0.7048611111111112,
    "test_roc_auc": 0.7604166666666667,
    "train_pr_auc": 0.3920009805990703,
    "val_pr_auc": 0.2813131313131313,
    "test_pr_auc": 0.3685739199525964,
    "overfitting_gap": 0.1055487902895601
  },
  "comparison_with_phase7": {
    "phase7_features": 88,
    "phase9_features": 88,
    "feature_reduction_pct": 0.0,
    "phase7_test_auc": 0.7604166666666667,
    "phase9_test_auc": 0.7604166666666667,
    "improvement_pct": 0.0
  },
  "all_feature_sets_tested": [
    {
      "feature_set": "all_features",
      "n_features": 88,
      "cv_train_auc": 0.8035030883963564,
      "cv_train_auc_std": 0.02963977890569644,
      "cv_test_auc": 0.7265991471215352,
      "cv_test_auc_std": 0.04817096974234974,
      "cv_pr_auc": 0.28934458855724665,
      "cv_pr_auc_std": 0.04625487561218988,
      "train_auc": 0.8321479374110953,
      "val_auc": 0.7048611111111112,
      "test_auc": 0.7604166666666667,
      "train_pr": 0.3920009805990703,
      "val_pr": 0.2813131313131313,
      "test_pr": 0.3685739199525964,
      "overfitting_gap": 0.1055487902895601
    },
    {
      "feature_set": "top_20",
      "n_features": 20,
      "cv_train_auc": 0.7778109993480742,
      "cv_train_auc_std": 0.026190008677349916,
      "cv_test_auc": 0.7093004942818376,
      "cv_test_auc_std": 0.051804933795824855,
      "cv_pr_auc": 0.268199123025617,
      "cv_pr_auc_std": 0.040078497863950444,
      "train_auc": 0.791488857278331,
      "val_auc": 0.671875,
      "test_auc": 0.795138888888889,
      "train_pr": 0.3073089104634813,
      "val_pr": 0.24176905108603322,
      "test_pr": 0.3499560080442433,
      "overfitting_gap": 0.08218836299649335
    },
    {
      "feature_set": "top_40",
      "n_features": 40,
      "cv_train_auc": 0.7899688571434627,
      "cv_train_auc_std": 0.017226398363775867,
      "cv_test_auc": 0.6894654164243715,
      "cv_test_auc_std": 0.028761722542734826,
      "cv_pr_auc": 0.2550744775306303,
      "cv_pr_auc_std": 0.04370219270918504,
      "train_auc": 0.8180022127390548,
      "val_auc": 0.7265625,
      "test_auc": 0.7777777777777777,
      "train_pr": 0.3444763166529258,
      "val_pr": 0.2606148162182645,
      "test_pr": 0.3843587718587719,
      "overfitting_gap": 0.1285367963146833
    },
    {
      "feature_set": "significant",
      "n_features": 21,
      "cv_train_auc": 0.7714247788736067,
      "cv_train_auc_std": 0.03745923098194149,
      "cv_test_auc": 0.6882608063578213,
      "cv_test_auc_std": 0.05200725119941768,
      "cv_pr_auc": 0.24365313191983567,
      "cv_pr_auc_std": 0.04136569891640732,
      "train_auc": 0.7906590801327644,
      "val_auc": 0.6649305555555556,
      "test_auc": 0.7795138888888888,
      "train_pr": 0.30888253907935326,
      "val_pr": 0.2526916007519456,
      "test_pr": 0.31689514130475444,
      "overfitting_gap": 0.10239827377494315
    },
    {
      "feature_set": "top_30",
      "n_features": 30,
      "cv_train_auc": 0.7815466553904393,
      "cv_train_auc_std": 0.0387938281723025,
      "cv_test_auc": 0.6868183433481941,
      "cv_test_auc_std": 0.05705297853915249,
      "cv_pr_auc": 0.2255453646176532,
      "cv_pr_auc_std": 0.03323771142567462,
      "train_auc": 0.8159080132764344,
      "val_auc": 0.7517361111111112,
      "test_auc": 0.75,
      "train_pr": 0.33738541217666745,
      "val_pr": 0.2658163265306122,
      "test_pr": 0.3434043927648579,
      "overfitting_gap": 0.12908966992824022
    },
    {
      "feature_set": "top_50",
      "n_features": 50,
      "cv_train_auc": 0.7951533509380555,
      "cv_train_auc_std": 0.02999397562501726,
      "cv_test_auc": 0.6820031336822383,
      "cv_test_auc_std": 0.05230569062003334,
      "cv_pr_auc": 0.21528190199403344,
      "cv_pr_auc_std": 0.041978214005491954,
      "train_auc": 0.8052789631737002,
      "val_auc": 0.6614583333333333,
      "test_auc": 0.7612847222222222,
      "train_pr": 0.31282048351813224,
      "val_pr": 0.2991501673613743,
      "test_pr": 0.4177899377754029,
      "overfitting_gap": 0.12327582949146187
    },
    {
      "feature_set": "rfe_selected",
      "n_features": 40,
      "cv_train_auc": 0.7912749721955002,
      "cv_train_auc_std": 0.0462787171739639,
      "cv_test_auc": 0.6754910512373199,
      "cv_test_auc_std": 0.03866565797684694,
      "cv_pr_auc": 0.21334840915776096,
      "cv_pr_auc_std": 0.038746349444499194,
      "train_auc": 0.7991939307728781,
      "val_auc": 0.7274305555555556,
      "test_auc": 0.7960069444444444,
      "train_pr": 0.32655922402044935,
      "val_pr": 0.2645523856342481,
      "test_pr": 0.4150245025245025,
      "overfitting_gap": 0.12370287953555825
    }
  ]
}